{
  "funding": {
    "afcn_6d967e47e071": {
      "first_seen": "2026-02-06T19:19:18.111452",
      "title": "\u00bb S-au publicat listele proiectelor culturale selectate pentru acordarea finan\u021b\u0103rilor, dup\u0103 etapa I de evaluare, in sesiunea de finan\u021bare proiecte culturale I/2013",
      "url": "https://www.afcn.ro/stiri/S-au-publicat-listele-proiectelor-culturale-selectate-pentru-acordarea-finan-rilor-dup-etapa-I-de-evaluare-in-sesiunea-de-finan-are-proiecte-culturale-I-2013-67.html",
      "source": "afcn",
      "deadline": "1 septembrie            2022",
      "matched_keywords": [
        "cultura",
        "cultural",
        "culturale"
      ]
    },
    "afcn_6c01090beeb3": {
      "first_seen": "2026-02-06T19:19:18.112677",
      "title": "\u00bb Invitatie pentru evaluarea proiectelor culturale 2013",
      "url": "https://www.afcn.ro/stiri/Invitatie-pentru-evaluarea-proiectelor-culturale-2013-72.html",
      "source": "afcn",
      "deadline": "1 septembrie            2022",
      "matched_keywords": [
        "cultura",
        "cultural",
        "culturale"
      ]
    },
    "fdsc_0f9d3cc6240b": {
      "first_seen": "2026-02-06T19:19:18.113881",
      "title": "Programe \u0219i proiecte",
      "url": "https://www.fdsc.ro/programe/",
      "source": "fdsc",
      "deadline": null,
      "matched_keywords": [
        "ong",
        "grant",
        "granturi",
        "inovare",
        "capacitare",
        "civic",
        "civica"
      ]
    },
    "fdsc_cc3b29ab8db0": {
      "first_seen": "2026-02-06T19:19:18.118861",
      "title": "Afl\u0103 mai multe",
      "url": "https://www.fdsc.ro/Programe_Proiecte/programul-cantonului-basel-stadt-in-romania/",
      "source": "fdsc",
      "deadline": null,
      "matched_keywords": [
        "capacitare"
      ]
    },
    "fdsc_71e10abe42b9": {
      "first_seen": "2026-02-06T19:19:18.120033",
      "title": "Afl\u0103 mai multe",
      "url": "https://www.fdsc.ro/Programe_Proiecte/raf-programul-efectiv-civic/",
      "source": "fdsc",
      "deadline": null,
      "matched_keywords": [
        "tineri",
        "copii",
        "ong",
        "capacitare",
        "civic"
      ]
    },
    "ngohub_5e12716a7d52": {
      "first_seen": "2026-02-06T19:19:18.130082",
      "title": "Funding Call",
      "url": "https://www.ngohub.ro/ro/funding-call",
      "source": "ngohub",
      "deadline": null,
      "matched_keywords": [
        "ong",
        "ngo",
        "grant"
      ]
    },
    "fdsc_94c2cfd937c5": {
      "first_seen": "2026-03-12T08:51:13.579301",
      "title": "FDSC lanseaz\u0103 LegiXplore ONG",
      "url": "https://www.fdsc.ro/fdsc-lanseaza-legixplore-ong/",
      "source": "fdsc",
      "deadline": null,
      "matched_keywords": [
        "ong",
        "digital",
        "capacitare"
      ]
    },
    "fdsc_97123b93d9e1": {
      "first_seen": "2026-05-19T11:22:30.947578",
      "title": "Dreptul de asociere nu poate fi restr\u00e2ns sub pretextul transparen\u021bei.",
      "url": "https://www.fdsc.ro/dreptul-de-asociere-nu-poate-fi-restrans-sub-pretextul-transparentei/",
      "source": "fdsc",
      "deadline": null,
      "matched_keywords": [
        "capacitare",
        "civic"
      ]
    },
    "ngohub_b87377070127": {
      "first_seen": "2026-06-12T11:45:45.921487",
      "title": "Programe UE pentru tineri",
      "url": "https://www.eurodesk.ro/pag-3",
      "source": "ngohub",
      "deadline": null,
      "matched_keywords": [
        "tineret",
        "tineri",
        "incluziune",
        "voluntariat"
      ]
    },
    "fonduri_structurale_1e2deb80c3a0": {
      "first_seen": "2026-06-13T10:32:31.441302",
      "title": "Sprijin pentru micro\u00eentreprinderile selectate prin proiectul Crowd4SME-NW \u00een cadrul \u201eCROWDFUNDMATCH\u201d Interreg Europe \u2013 apel pilotApelul de proiecte ofer\u0103 granturi pentru micro\u00eentreprinderi, sprijinind investi\u021bii \u00een echipamente, tehnologii \u0219i servicii pentru cre\u0219terea competitivi...Programul Regional Nord-Vest22 Iun. 2026 - 10 Iul. 2026Finan\u021bare activ\u0103Vezi mai multe detalii",
      "url": "https://www.fonduri-structurale.ro/finantari/2298/sprijin-pentru-microintreprinderile-selectate-prin-proiectul-crowd4-sme-nw-in-cadrul-crowdfundmatch-interreg-europe-apel-pilot",
      "source": "fonduri_structurale",
      "deadline": null,
      "matched_keywords": [
        "granturi"
      ]
    }
  },
  "last_updated": "2026-06-13T10:32:31.738662"
}